dynapython/__init__.py
dynapython/client.py
dynapython-1.0.0.1.dist-info/LICENSE
dynapython-1.0.0.1.dist-info/METADATA
dynapython-1.0.0.1.dist-info/WHEEL
dynapython-1.0.0.1.dist-info/top_level.txt
dynapython-1.0.0.1.dist-info/RECORD
