Metadata-Version: 2.1
Name: dynapython
Version: 1.0.0.1
Summary: Python connector for the Dynizer
Home-page: https://github.com/Dynactionize/Dyna-Python
Author: Dynactionize NV
Author-email: info-belgium@dynationize.com
License: UNKNOWN
Platform: UNKNOWN
Classifier: Programming Language :: Python :: 3
Classifier: License :: OSI Approved :: MIT License
Classifier: Operating System :: OS Independent
Requires-Dist: dynagatewaytypes
